pundas/__init__.py
pundas/bda1.py
pundas/bda2.py
pundas/bda3.py
pundas/bda4.py
pundas/bi2.py
pundas/bi5.py
pundas/bi6.py
pundas/dl1.py
pundas/dl2.py
pundas/dl3.py
pundas/dl4.py
pundas/dl5.py
pundas-0.6.0.dist-info/METADATA
pundas-0.6.0.dist-info/WHEEL
pundas-0.6.0.dist-info/top_level.txt
pundas-0.6.0.dist-info/RECORD
